discord_webhooks/__init__.py
discord_webhooks/enums.py
discord_webhooks/types.py
discord_webhooks/webhook_service.py
discord_webhooks_python-1.0.0.dist-info/LICENSE
discord_webhooks_python-1.0.0.dist-info/METADATA
discord_webhooks_python-1.0.0.dist-info/WHEEL
discord_webhooks_python-1.0.0.dist-info/top_level.txt
discord_webhooks_python-1.0.0.dist-info/RECORD
