Metadata-Version: 2.1
Name: discord-webhooks-python
Version: 1.0.0
Summary: A clear example of how you should implement Discord webhooks.
Author-email: Isabelle Phoebe <hi@uwu.gal>
License: MIT License
Project-URL: Homepage, https://github.com/Maki-gg/discord-webhook-python
Project-URL: Bug Tracker, https://github.com/Maki-gg/discord-webhook-python/issues
Classifier: Development Status :: 5 - Production/Stable
Classifier: License :: OSI Approved :: MIT License
Classifier: Intended Audience :: Developers
Classifier: Natural Language :: English
Classifier: Operating System :: OS Independent
Classifier: Programming Language :: Python :: 3.8
Classifier: Programming Language :: Python :: 3.9
Classifier: Programming Language :: Python :: 3.10
Classifier: Programming Language :: Python :: 3.11
Classifier: Programming Language :: Python :: 3.12
Classifier: Topic :: Internet
Classifier: Topic :: Software Development :: Libraries
Classifier: Topic :: Software Development :: Libraries :: Python Modules
Classifier: Topic :: Utilities
Classifier: Typing :: Typed
License-File: LICENSE
Requires-Dist: fastapi
Requires-Dist: PyNaCl
Requires-Dist: uvicorn
